{"cameraMode":{"drawMode":0,"name":"Shaded","section":"Shading Mode"},"sceneLighting":true,"audioPlay":false,"sceneViewState":{"m_AlwaysRefresh":false,"showFog":true,"showSkybox":true,"showFlares":true,"showImageEffects":true,"showParticleSystems":true,"showVisualEffectGraphs":true,"m_FxEnabled":true},"in2DMode":false,"pivot":{"x":215.12319946289063,"y":-53.53945541381836,"z":-99.82598876953125},"rotation":{"x":-0.0827166959643364,"y":-0.8281176686286926,"z":0.1395561844110489,"w":-0.5419293642044067},"size":138.5331268310547,"orthographic":false}